odoo/addons/l10n_br_pos_cfe/README.rst
odoo/addons/l10n_br_pos_cfe/__init__.py
odoo/addons/l10n_br_pos_cfe/__manifest__.py
odoo/addons/l10n_br_pos_cfe/demo/pos_config_demo.xml
odoo/addons/l10n_br_pos_cfe/demo/pos_payment_method_demo.xml
odoo/addons/l10n_br_pos_cfe/i18n/l10n_br_pos_cfe.pot
odoo/addons/l10n_br_pos_cfe/i18n/pt_BR.po
odoo/addons/l10n_br_pos_cfe/models/__init__.py
odoo/addons/l10n_br_pos_cfe/models/pos_config.py
odoo/addons/l10n_br_pos_cfe/models/pos_order.py
odoo/addons/l10n_br_pos_cfe/models/pos_payment_method.py
odoo/addons/l10n_br_pos_cfe/readme/CONFIGURE.rst
odoo/addons/l10n_br_pos_cfe/readme/CONTRIBUTORS.rst
odoo/addons/l10n_br_pos_cfe/readme/CREDITS.rst
odoo/addons/l10n_br_pos_cfe/readme/DESCRIPTION.rst
odoo/addons/l10n_br_pos_cfe/readme/HISTORY.rst
odoo/addons/l10n_br_pos_cfe/readme/INSTALL.rst
odoo/addons/l10n_br_pos_cfe/static/description/icon.png
odoo/addons/l10n_br_pos_cfe/static/description/index.html
odoo/addons/l10n_br_pos_cfe/static/src/css/pos.css
odoo/addons/l10n_br_pos_cfe/static/src/js/devices.js
odoo/addons/l10n_br_pos_cfe/static/src/js/fiscal_cfe.js
odoo/addons/l10n_br_pos_cfe/static/src/js/models.js
odoo/addons/l10n_br_pos_cfe/static/src/js/ChromeWidgets/ProxyStatus.js
odoo/addons/l10n_br_pos_cfe/static/src/js/OrderManagementScreen/ReprintReceiptScreen.js
odoo/addons/l10n_br_pos_cfe/static/src/js/PaymentScreen/PaymentScreen.js
odoo/addons/l10n_br_pos_cfe/static/src/js/ReceiptScreen/OrderFooterReceipt.js
odoo/addons/l10n_br_pos_cfe/static/src/js/ReceiptScreen/OrderHeaderReceipt.js
odoo/addons/l10n_br_pos_cfe/static/src/js/ReceiptScreen/OrderPaymentReceipt.js
odoo/addons/l10n_br_pos_cfe/static/src/js/ReceiptScreen/OrderRowReceipt.js
odoo/addons/l10n_br_pos_cfe/static/src/js/ReceiptScreen/OrderSubtitleReceipt.js
odoo/addons/l10n_br_pos_cfe/static/src/js/ReceiptScreen/OrderTotalsReceipt.js
odoo/addons/l10n_br_pos_cfe/static/src/js/ReceiptScreen/ReceiptScreen.js
odoo/addons/l10n_br_pos_cfe/static/src/js/ReceiptScreen/SatOrderReceipt.js
odoo14_addon_l10n_br_pos_cfe-14.0.1.4.2.dist-info/METADATA
odoo14_addon_l10n_br_pos_cfe-14.0.1.4.2.dist-info/WHEEL
odoo14_addon_l10n_br_pos_cfe-14.0.1.4.2.dist-info/top_level.txt
odoo14_addon_l10n_br_pos_cfe-14.0.1.4.2.dist-info/RECORD
